{
  "id": "elephant-core-diet",
  "animalSlug": "african-elephant",
  "slug": "elephant-core-diet",
  "fileName": "elephant-core-diet-01-1200.webp",
  "src": "/images/animals/african-elephant/web/elephant-core-diet-01-1200.webp",
  "width": 1200,
  "height": 745,
  "alt": "Savanna elephant eating dry grass with trunk in open field",
  "caption": "Elephants use their trunks to pull grasses, leaves, and bark for food.",
  "attributionText": "Photo by Bernard DUPONT via Wikimedia Commons, CC BY-SA 2.0",
  "attributionHtml": "Photo by <a href=\"https://commons.wikimedia.org/wiki/File:Savanna_Elephant_(Loxodonta_africana)_eating_dry_grass.jpg\">Bernard DUPONT</a> via <a href=\"https://commons.wikimedia.org/\">Wikimedia Commons</a>, <a href=\"https://creativecommons.org/licenses/by-sa/2.0\">CC BY-SA 2.0</a>",
  "source": {
    "sourceName": "Wikimedia Commons",
    "sourceUrl": "https://commons.wikimedia.org/wiki/File:Savanna_Elephant_(Loxodonta_africana)_eating_dry_grass.jpg",
    "creatorName": "Bernard DUPONT",
    "licenseName": "CC BY-SA 2.0",
    "licenseUrl": "https://creativecommons.org/licenses/by-sa/2.0",
    "requiresAttribution": true,
    "downloadedAt": "2026-06-25T14:48:29.497Z",
    "reviewedBy": "editor@wildlifedb.local"
  },
  "imageType": "diet",
  "galleryTopics": [
    "diet"
  ],
  "featuredOnPages": [
    "core"
  ],
  "location": "African savanna",
  "acquisitionNotes": "Core article diet image sourced from Wikimedia Commons; kept separate from gallery image set. Local WebP ingested from https://upload.wikimedia.org/wikipedia/commons/2/29/Savanna_Elephant_%28Loxodonta_africana%29_eating_dry_grass.jpg",
  "updatedAt": "2026-06-25T14:48:29.497Z",
  "srcSet": {
    "web1200": "/images/animals/african-elephant/web/elephant-core-diet-01-1200.webp",
    "thumbnail400": "/images/animals/african-elephant/thumbnails/elephant-core-diet-01-400.webp",
    "original": "/images/animals/african-elephant/web/elephant-core-diet-01-1200.webp"
  }
}
