{
  "id": "giraffe-diet",
  "animalSlug": "giraffe",
  "slug": "giraffe-diet",
  "fileName": "Giraffe feeding, Tanzania.jpg",
  "src": "https://upload.wikimedia.org/wikipedia/commons/d/d2/Giraffe_feeding%2C_Tanzania.jpg",
  "width": 1600,
  "height": 1066,
  "alt": "Giraffe reaching into a tree to feed",
  "caption": "A giraffe uses its long tongue and lips to pull leaves around thorns.",
  "attributionText": "Photo by Muhammad Mahdi Karim via Wikimedia Commons, GFDL 1.2",
  "attributionHtml": "Photo by <a href=\"https://commons.wikimedia.org/wiki/File:Giraffe_feeding%2C_Tanzania.jpg\">Muhammad Mahdi Karim</a> via <a href=\"https://commons.wikimedia.org/\">Wikimedia Commons</a>, <a href=\"http://www.gnu.org/licenses/old-licenses/fdl-1.2.html\">GFDL 1.2</a>",
  "source": {
    "sourceName": "Wikimedia Commons",
    "sourceUrl": "https://commons.wikimedia.org/wiki/File:Giraffe_feeding%2C_Tanzania.jpg",
    "creatorName": "Muhammad Mahdi Karim",
    "licenseName": "GFDL 1.2",
    "licenseUrl": "http://www.gnu.org/licenses/old-licenses/fdl-1.2.html",
    "requiresAttribution": true,
    "downloadedAt": "2026-06-23T05:02:35.575Z",
    "reviewedBy": "editor@kidsfacts.local"
  },
  "imageType": "diet",
  "galleryTopics": [
    "diet"
  ],
  "featuredOnPages": [
    "gallery"
  ],
  "location": "Tanzania",
  "acquisitionNotes": "Manually curated giraffe diet image with verified species identification.",
  "updatedAt": "2026-06-23T05:02:35.575Z"
}
