{
  "id": "red-panda-core-baby",
  "animalSlug": "red-panda",
  "slug": "red-panda-core-baby",
  "fileName": "red-panda-core-baby-01-1200.webp",
  "src": "/images/animals/red-panda/web/red-panda-core-baby-01-1200.webp",
  "width": 1200,
  "height": 803,
  "alt": "Young red panda cub resting on a mossy branch",
  "caption": "Red panda cubs stay with their mother for months after birth.",
  "attributionText": "Photo by Sayanrony9563 via Wikimedia Commons, CC BY-SA 4.0",
  "attributionHtml": "Photo by <a href=\"https://commons.wikimedia.org/wiki/File:The_red_panda_(Ailurus_fulgens).jpg\">Sayanrony9563</a> via <a href=\"https://commons.wikimedia.org/\">Wikimedia Commons</a>, <a href=\"https://creativecommons.org/licenses/by-sa/4.0\">CC BY-SA 4.0</a>",
  "source": {
    "sourceName": "Wikimedia Commons",
    "sourceUrl": "https://commons.wikimedia.org/wiki/File:The_red_panda_(Ailurus_fulgens).jpg",
    "creatorName": "Sayanrony9563",
    "licenseName": "CC BY-SA 4.0",
    "licenseUrl": "https://creativecommons.org/licenses/by-sa/4.0",
    "requiresAttribution": true,
    "downloadedAt": "2026-06-25T15:09:22.483Z",
    "reviewedBy": "editor@wildlifedb.local"
  },
  "imageType": "baby",
  "galleryTopics": [
    "baby"
  ],
  "featuredOnPages": [
    "core"
  ],
  "location": "Himalayas",
  "acquisitionNotes": "Core article baby image — verified Commons file. Local WebP ingested from https://upload.wikimedia.org/wikipedia/commons/8/87/The_red_panda_%28Ailurus_fulgens%29.jpg",
  "updatedAt": "2026-06-25T15:09:22.483Z",
  "srcSet": {
    "web1200": "/images/animals/red-panda/web/red-panda-core-baby-01-1200.webp",
    "thumbnail400": "/images/animals/red-panda/thumbnails/red-panda-core-baby-01-400.webp",
    "original": "/images/animals/red-panda/web/red-panda-core-baby-01-1200.webp"
  }
}
