{
  "id": "chameleon-core-family",
  "animalSlug": "chameleon",
  "slug": "chameleon-core-family",
  "fileName": "chameleon-core-family-01-1200.webp",
  "src": "/images/animals/chameleon/web/chameleon-core-family-01-1200.webp",
  "width": 1200,
  "height": 900,
  "alt": "A pair of panther chameleons on a branch in Madagascar's rainforest",
  "caption": "Chameleons are mostly solitary but meet briefly during mating season.",
  "attributionText": "Photo by Kristof Magnusson via Wikimedia Commons, CC BY-SA 4.0",
  "attributionHtml": "Photo by <a href=\"https://commons.wikimedia.org/wiki/File:Veiled_chameleon_Chamaeleo_calyptratus_Aquarium_Berlin_Zoo.jpg\">Kristof Magnusson</a> via <a href=\"https://commons.wikimedia.org/\">Wikimedia Commons</a>, <a href=\"https://creativecommons.org/licenses/by-sa/4.0\">CC BY-SA 4.0</a>",
  "source": {
    "sourceName": "Wikimedia Commons",
    "sourceUrl": "https://commons.wikimedia.org/wiki/File:Veiled_chameleon_Chamaeleo_calyptratus_Aquarium_Berlin_Zoo.jpg",
    "creatorName": "Kristof Magnusson",
    "licenseName": "CC BY-SA 4.0",
    "licenseUrl": "https://creativecommons.org/licenses/by-sa/4.0",
    "requiresAttribution": true,
    "downloadedAt": "2026-06-25T14:49:56.391Z",
    "reviewedBy": "editor@wildlifedb.local"
  },
  "imageType": "family",
  "galleryTopics": [
    "family"
  ],
  "featuredOnPages": [
    "core"
  ],
  "location": "Berlin, Germany",
  "acquisitionNotes": "Core article image curated separately from the chameleon gallery set. Re-synced canonical Commons URL. Local WebP ingested from https://upload.wikimedia.org/wikipedia/commons/f/f0/Veiled_chameleon_Chamaeleo_calyptratus_Aquarium_Berlin_Zoo.jpg",
  "updatedAt": "2026-06-25T14:49:56.391Z",
  "srcSet": {
    "web1200": "/images/animals/chameleon/web/chameleon-core-family-01-1200.webp",
    "thumbnail400": "/images/animals/chameleon/thumbnails/chameleon-core-family-01-400.webp",
    "original": "/images/animals/chameleon/web/chameleon-core-family-01-1200.webp"
  }
}
