{
  "id": "tasmanian-devil-core-habitat",
  "animalSlug": "tasmanian-devil",
  "slug": "tasmanian-devil-core-habitat",
  "fileName": "tasmanian-devil-core-habitat-01-1200.webp",
  "alt": "A Tasmanian Devil navigating its natural environment",
  "caption": "They make their home in diverse habitats where they can find shelter and thrive.",
  "galleryTopics": [
    "habitat"
  ],
  "featuredOnPages": [
    "core"
  ],
  "imageType": "habitat",
  "location": "Unknown",
  "src": "/images/animals/tasmanian-devil/web/tasmanian-devil-core-habitat-01-1200.webp",
  "width": 1200,
  "height": 798,
  "attributionText": "Photo by Sleeps-Darkly via Wikimedia Commons, CC BY-SA 4.0",
  "attributionHtml": "Photo by <a href=\"https://commons.wikimedia.org/wiki/File:Tasmanian_devil_(Sarcophilus_harrisii)_2,_Auckland_Zoo,_2023-04-22.jpg\">Sleeps-Darkly</a> via <a href=\"https://commons.wikimedia.org/\">Wikimedia Commons</a>, <a href=\"https://creativecommons.org/licenses/by-sa/4.0\">CC BY-SA 4.0</a>",
  "source": {
    "sourceName": "Wikimedia Commons",
    "sourceUrl": "https://commons.wikimedia.org/wiki/File:Tasmanian_devil_(Sarcophilus_harrisii)_2,_Auckland_Zoo,_2023-04-22.jpg",
    "creatorName": "Sleeps-Darkly",
    "licenseName": "CC BY-SA 4.0",
    "licenseUrl": "https://creativecommons.org/licenses/by-sa/4.0",
    "requiresAttribution": true,
    "downloadedAt": "2026-06-26T08:17:54.830Z",
    "reviewedBy": "editor@wildlifedb.local"
  },
  "acquisitionNotes": "Manually verified tasmanian-devil image for habitat. Local WebP ingested from https://upload.wikimedia.org/wikipedia/commons/a/a8/Tasmanian_devil_%28Sarcophilus_harrisii%29_2%2C_Auckland_Zoo%2C_2023-04-22.jpg",
  "updatedAt": "2026-06-26T08:17:54.830Z",
  "srcSet": {
    "web1200": "/images/animals/tasmanian-devil/web/tasmanian-devil-core-habitat-01-1200.webp",
    "thumbnail400": "/images/animals/tasmanian-devil/thumbnails/tasmanian-devil-core-habitat-01-400.webp",
    "original": "/images/animals/tasmanian-devil/web/tasmanian-devil-core-habitat-01-1200.webp"
  }
}
